pycounts_imtvwy/__init__.py
pycounts_imtvwy/plotting.py
pycounts_imtvwy/pycounts_imtvwy.py
pycounts_imtvwy-0.2.2.dist-info/LICENSE
pycounts_imtvwy-0.2.2.dist-info/WHEEL
pycounts_imtvwy-0.2.2.dist-info/METADATA
pycounts_imtvwy-0.2.2.dist-info/RECORD
